tkiv/tkiv.py
tkiv-0.1.0.dist-info/DESCRIPTION.rst
tkiv-0.1.0.dist-info/METADATA
tkiv-0.1.0.dist-info/RECORD
tkiv-0.1.0.dist-info/WHEEL
tkiv-0.1.0.dist-info/entry_points.txt
tkiv-0.1.0.dist-info/metadata.json
tkiv-0.1.0.dist-info/top_level.txt
