Metadata-Version: 2.0
Name: tkiv
Version: 0.1.0
Summary: Just a tkinter image viewer
Home-page: UNKNOWN
Author: Danilo Souza Morães
Author-email: greendhulke@gmail.com
License: MIT
Platform: UNKNOWN
Classifier: License :: OSI Approved :: MIT License
Classifier: Programming Language :: Python :: 3.4
Classifier: Programming Language :: Python :: 3.5
Classifier: Programming Language :: Python :: 3.6
Classifier: Programming Language :: Python :: Implementation :: CPython
Classifier: Programming Language :: Python :: Implementation :: PyPy
Requires-Dist: pillow
